brian2cuda/__init__.py
brian2cuda/_version.py
brian2cuda/binomial.py
brian2cuda/codeobject.py
brian2cuda/cuda_generator.py
brian2cuda/cuda_prefs.py
brian2cuda/device.py
brian2cuda/timedarray.py
brian2cuda/brianlib/clocks.h
brian2cuda/brianlib/common_math.h
brian2cuda/brianlib/cudaVector.h
brian2cuda/brianlib/cuda_utils.h
brian2cuda/brianlib/curand_buffer.h
brian2cuda/brianlib/dynamic_array.h
brian2cuda/brianlib/spikequeue.h
brian2cuda/brianlib/stdint_compat.h
brian2cuda/sphinxext/__init__.py
brian2cuda/sphinxext/briandoc.py
brian2cuda/sphinxext/docscrape.py
brian2cuda/sphinxext/docscrape_sphinx.py
brian2cuda/sphinxext/examplefinder.py
brian2cuda/sphinxext/generate_examples.py
brian2cuda/sphinxext/generate_reference.py
brian2cuda/templates/common_group.cu
brian2cuda/templates/common_synapses.cu
brian2cuda/templates/group_variable_set.cu
brian2cuda/templates/group_variable_set_conditional.cu
brian2cuda/templates/main.cu
brian2cuda/templates/makefile
brian2cuda/templates/network.cu
brian2cuda/templates/objects.cu
brian2cuda/templates/rand.cu
brian2cuda/templates/ratemonitor.cu
brian2cuda/templates/reset.cu
brian2cuda/templates/run.cu
brian2cuda/templates/spatialstateupdate.cu
brian2cuda/templates/spikegenerator.cu
brian2cuda/templates/spikemonitor.cu
brian2cuda/templates/statemonitor.cu
brian2cuda/templates/stateupdate.cu
brian2cuda/templates/summed_variable.cu
brian2cuda/templates/synapses.cu
brian2cuda/templates/synapses_classes.cu
brian2cuda/templates/synapses_create_array.cu
brian2cuda/templates/synapses_create_generator.cu
brian2cuda/templates/synapses_push_spikes.cu
brian2cuda/templates/threshold.cu
brian2cuda/templates/win_makefile
brian2cuda/tests/__init__.py
brian2cuda/tests/conftest.py
brian2cuda/tests/func_def_cuda.cu
brian2cuda/tests/func_def_cuda.h
brian2cuda/tests/test_cpp_cuda_consistency.py
brian2cuda/tests/test_cuda_generator.py
brian2cuda/tests/test_cuda_standalone.py
brian2cuda/tests/test_functions.py
brian2cuda/tests/test_gpu_detection.py
Brian2Cuda-1.0a7.dist-info/LICENSE
Brian2Cuda-1.0a7.dist-info/METADATA
Brian2Cuda-1.0a7.dist-info/WHEEL
Brian2Cuda-1.0a7.dist-info/top_level.txt
Brian2Cuda-1.0a7.dist-info/RECORD
