Metadata-Version: 2.2
Name: Brian2Cuda
Version: 1.0a7
Summary: A Brian2 extension to simulate spiking neural networks on GPUs
Author: Denis Alevi, Moritz Augustin, Marcel Stimberg
Project-URL: Documentation, https://brian2cuda.readthedocs.io/
Project-URL: Source, https://github.com/brian-team/brian2cuda
Project-URL: Tracker, https://github.com/brian-team/brian2cuda/issues
Keywords: computational neuroscience,simulation,neural networks,spiking neurons,gpu,cuda
Classifier: Development Status :: 3 - Alpha
Classifier: Intended Audience :: Science/Research
Classifier: License :: OSI Approved :: GNU General Public License v3 (GPLv3)
Classifier: Natural Language :: English
Classifier: Operating System :: OS Independent
Classifier: Programming Language :: Python
Classifier: Programming Language :: Python :: 3
Classifier: Environment :: GPU :: NVIDIA CUDA
Classifier: Topic :: Scientific/Engineering :: Bio-Informatics
Requires-Python: >=3.10
License-File: LICENSE
Requires-Dist: brian2==2.8.0
Provides-Extra: test
Requires-Dist: pytest; extra == "test"
Requires-Dist: pytest-xdist>=1.22.3; extra == "test"
Provides-Extra: docs
Requires-Dist: sphinx>=1.8; extra == "docs"
